[
  [
    {
      "team": "Dolphins",
      "points": "14"
    },
    {
      "team": "Steelers",
      "points": "27"
    }
  ],
  [
    {
      "team": "Seahawks",
      "points": "27"
    },
    {
      "team": "Falcons",
      "points": "20"
    }
  ],
  [
    {
      "team": "Buccaneers",
      "points": "23"
    },
    {
      "team": "Titans",
      "points": "27"
    }
  ],
  [
    {
      "team": "Broncos",
      "points": "13"
    },
    {
      "team": "Colts",
      "points": "15"
    }
  ],
  [
    {
      "team": "Bengals",
      "points": "10"
    },
    {
      "team": "Rams",
      "points": "24"
    }
  ],
  [
    {
      "team": "Cardinals",
      "points": "9"
    },
    {
      "team": "Saints",
      "points": "31"
    }
  ],
  [
    {
      "team": "Jets",
      "points": "15"
    },
    {
      "team": "Jaguars",
      "points": "29"
    }
  ],
  [
    {
      "team": "Chargers",
      "points": "17"
    },
    {
      "team": "Bears",
      "points": "16"
    }
  ],
  [
    {
      "team": "Eagles",
      "points": "31"
    },
    {
      "team": "Bills",
      "points": "13"
    }
  ],
  [
    {
      "team": "Giants",
      "points": "26"
    },
    {
      "team": "Lions",
      "points": "31"
    }
  ],
  [
    {
      "team": "Panthers",
      "points": "13"
    },
    {
      "team": "49ers",
      "points": "51"
    }
  ],
  [
    {
      "team": "Browns",
      "points": "13"
    },
    {
      "team": "Patriots",
      "points": "27"
    }
  ],
  [
    {
      "team": "Raiders",
      "points": "24"
    },
    {
      "team": "Texans",
      "points": "27"
    }
  ],
  [
    {
      "team": "Packers",
      "points": "31"
    },
    {
      "team": "Chiefs",
      "points": "24"
    }
  ],
  [
    {
      "team": "Redskins",
      "points": "9"
    },
    {
      "team": "Vikings",
      "points": "19"
    }
  ]
]